XeprAPI/__init__.py
XeprAPI/libxeprapi.so
XeprAPI/libxeprapi_32.so
XeprAPI/main.py
XeprAPI-0.61.1.dist-info/METADATA
XeprAPI-0.61.1.dist-info/WHEEL
XeprAPI-0.61.1.dist-info/top_level.txt
XeprAPI-0.61.1.dist-info/RECORD
