Metadata-Version: 2.1
Name: XeprAPI
Version: 0.61.1
Summary: Python interface for for Bruker Xepr.
Author: Bruker Biospin
Author-email: ss2151@cam.ac.uk
License: MIT
Classifier: License :: OSI Approved :: MIT License
Classifier: Operating System :: Unix
Classifier: Programming Language :: Python
Classifier: Programming Language :: Python :: 3.6
Classifier: Programming Language :: Python :: 3.7
Classifier: Programming Language :: Python :: 3.8
Requires-Python: >=3.6
Requires-Dist: numpy >=1.2.1
